LICENSE.txt
README.md
setup.py
pyLense/Lense.py
pyLense/__init__.py
pyLense.egg-info/PKG-INFO
pyLense.egg-info/SOURCES.txt
pyLense.egg-info/dependency_links.txt
pyLense.egg-info/top_level.txt