Metadata-Version: 2.1
Name: pyLense
Version: 0.0.1
Summary: This is a simple url/link checker API
Home-page: https://t.me/Neuralp
Author: The Neurals
Keywords: url ckeck,link check,link,url
Classifier: Programming Language :: Python :: 3
Classifier: License :: OSI Approved :: MIT License
Classifier: Operating System :: OS Independent
Requires-Python: >=3.6
License-File: LICENSE.txt
